{
  "skillTags": [
    { "id": 1, "type": "skill", "title": "Python" },
    { "id": 2, "type": "skill", "title": "Django" },
    { "id": 3, "type": "skill", "title": "FastAPI" },
    { "id": 4, "type": "skill", "title": "React" },
    { "id": 5, "type": "skill", "title": "TypeScript" },
    { "id": 6, "type": "skill", "title": "SQL" },
    { "id": 7, "type": "skill", "title": "pandas" },
    { "id": 8, "type": "skill", "title": "Kubernetes" },
    { "id": 9, "type": "skill", "title": "Docker" },
    { "id": 10, "type": "skill", "title": "AWS" },
    { "id": 11, "type": "skill", "title": "Figma" },
    { "id": 12, "type": "skill", "title": "GA(Google Analytics)" },
    { "id": 13, "type": "skill", "title": "Terraform" },
    { "id": 14, "type": "skill", "title": "Java" },
    { "id": 15, "type": "skill", "title": "Spring" },
    { "id": 16, "type": "skill", "title": "Node.js" }
  ],
  "categoryTags": [
    { "id": 101, "type": "category", "title": "서버/백엔드" },
    { "id": 102, "type": "category", "title": "프론트엔드" },
    { "id": 103, "type": "category", "title": "데이터" },
    { "id": 104, "type": "category", "title": "기획/PM" },
    { "id": 105, "type": "category", "title": "디자인" },
    { "id": 106, "type": "category", "title": "인프라/DevOps" },
    { "id": 107, "type": "category", "title": "마케팅" }
  ],
  "attractionTags": [
    { "id": 201, "type": "attraction", "title": "자율출퇴근" },
    { "id": 202, "type": "attraction", "title": "재택근무" },
    { "id": 203, "type": "attraction", "title": "스톡옵션" },
    { "id": 204, "type": "attraction", "title": "최신 장비 지원" },
    { "id": 205, "type": "attraction", "title": "자기계발비 지원" },
    { "id": 206, "type": "attraction", "title": "유연근무제" }
  ],
  "companies": [
    {
      "id": "c1",
      "name": "테크노바",
      "color": "#2563eb",
      "description": "중소기업 업무 자동화를 돕는 클라우드 SaaS 스타트업입니다. 현재 800여 개 기업이 사용 중입니다.",
      "benefits": "자율출퇴근제 · 최신 장비 지원 · 연 200만원 자기계발비 지원 · 점심/저녁 식대 지원 · 3년차 리프레시 휴가(2주)",
      "cultureTagIds": [201, 204, 205],
      "avgSalary": 51000000
    },
    {
      "id": "c2",
      "name": "블루웨일랩스",
      "color": "#0891b2",
      "description": "5만여 이커머스 판매자가 사용하는 정산/재고 대시보드를 만듭니다.",
      "benefits": "주 4.5일제 시범 운영 · 도서 구입비 무제한 · 사내 스터디 지원 · 신규 입사자 웰컴 키트",
      "cultureTagIds": [206],
      "avgSalary": 48000000
    },
    {
      "id": "c3",
      "name": "그린소프트",
      "color": "#16a34a",
      "description": "친환경 소비 데이터를 분석해 리테일 기업에 인사이트를 제공합니다.",
      "benefits": "재택근무 주 2회 · 개인별 분석 서버 지급 · 컨퍼런스 참가비 지원",
      "cultureTagIds": [202],
      "avgSalary": 55000000
    },
    {
      "id": "c4",
      "name": "파인애플커머스",
      "color": "#f59e0b",
      "description": "도심형 새벽배송 인프라를 직접 구축/운영하는 커머스 기업입니다.",
      "benefits": "상시 채용, 즉시 입사 가능 · 전 직원 신선식품 정기구독 제공 · 명절 상여금 지급",
      "cultureTagIds": [],
      "avgSalary": 49000000
    },
    {
      "id": "c5",
      "name": "오로라디자인",
      "color": "#9333ea",
      "description": "여러 핀테크 기업의 앱/웹 UX를 설계하는 전문 스튜디오입니다.",
      "benefits": "최신 디자인 툴 라이선스 전 직원 지급 · 외부 디자인 컨퍼런스 참가 지원 · 자유복장",
      "cultureTagIds": [204],
      "avgSalary": 47000000
    },
    {
      "id": "c6",
      "name": "넥스트페이먼츠",
      "color": "#1d4ed8",
      "description": "연 20조원 규모의 결제를 처리하는 결제 인프라 기업입니다.",
      "benefits": "국내 최고 수준 연봉 · 스톡옵션 지급 · 최신 장비 및 듀얼 모니터 지원",
      "cultureTagIds": [203, 204],
      "avgSalary": 58000000
    },
    {
      "id": "c7",
      "name": "클라우드메이트",
      "color": "#0f766e",
      "description": "여러 클라우드(AWS/GCP/Azure)를 통합 관리하는 SaaS를 제공합니다.",
      "benefits": "클라우드 자격증 취득 비용 전액 지원 · 사내 세미나/발표 문화 · 유연근무제",
      "cultureTagIds": [206],
      "avgSalary": 53000000
    },
    {
      "id": "c8",
      "name": "스퀘어푸드",
      "color": "#db2777",
      "description": "1인가구를 위한 밀키트 정기구독 서비스를 운영하는 푸드테크 기업입니다.",
      "benefits": "매달 자사 밀키트 무상 제공 · 마케팅 툴/광고비 운영 재량권 부여 · 우수사원 해외연수",
      "cultureTagIds": [],
      "avgSalary": 45000000
    }
  ],
  "jobs": [
    {
      "id": "j1",
      "companyId": "c1",
      "companyName": "테크노바",
      "companyColor": "#2563eb",
      "category": "서버/백엔드",
      "position": "백엔드 개발자 (Python/Django)",
      "location": "서울 강남구",
      "dueTime": "2026-08-15",
      "applyUrl": "https://example.com/careers/technova/backend",
      "skillTagIds": [1, 2, 3],
      "salary": { "newHire": 42000000, "average": 51000000 },
      "intro": "테크노바는 중소기업의 반복 업무를 자동화하는 SaaS 플랫폼을 만듭니다. 현재 800여 개 기업이 사용 중입니다.",
      "mainTasks": "백엔드 API 설계 및 개발 · DB 스키마 설계 및 최적화 · 서비스 성능/장애 대응",
      "requirements": "Python 기반 서비스 개발 경험 3년 이상 · RDB 설계 경험",
      "preferredPoints": "Django 또는 FastAPI 실무 경험 · AWS 인프라 운영 경험",
      "hireRounds": "서류전형 → 실무면접 → 임원면접 → 처우협의",
      "benefits": "자율출퇴근제 · 최신 장비 지원 · 연 200만원 자기계발비 지원",
      "promoImages": [
        { "label": "사무실 전경", "bg": "#1e3a8a" },
        { "label": "팀 워크샵", "bg": "#2563eb" }
      ]
    },
    {
      "id": "j2",
      "companyId": "c2",
      "companyName": "블루웨일랩스",
      "companyColor": "#0891b2",
      "category": "프론트엔드",
      "position": "프론트엔드 개발자 (React)",
      "location": "서울 성동구",
      "dueTime": "2026-07-31",
      "applyUrl": "https://example.com/careers/bluewhale/frontend",
      "skillTagIds": [4, 5],
      "salary": { "newHire": 40000000, "average": 48000000 },
      "intro": "블루웨일랩스는 5만여 이커머스 판매자가 사용하는 정산/재고 대시보드를 만듭니다.",
      "mainTasks": "React 기반 대시보드 개발 · 디자인 시스템 컴포넌트 개발 · 성능 최적화",
      "requirements": "React 실무 경험 2년 이상 · TypeScript 사용 경험",
      "preferredPoints": "대용량 테이블/차트 렌더링 최적화 경험 · 디자인 시스템 구축 경험",
      "hireRounds": "서류전형 → 과제전형 → 실무면접 → 최종면접",
      "benefits": "주 4.5일제 시범 운영 · 도서 구입비 무제한",
      "promoImages": [{ "label": "개발팀 회의", "bg": "#0e7490" }]
    },
    {
      "id": "j3",
      "companyId": "c3",
      "companyName": "그린소프트",
      "companyColor": "#16a34a",
      "category": "데이터",
      "position": "데이터 분석가",
      "location": "경기 성남시",
      "dueTime": "2026-08-05",
      "applyUrl": "https://example.com/careers/greensoft/data-analyst",
      "skillTagIds": [6, 7],
      "salary": { "newHire": 43000000, "average": 55000000 },
      "intro": "그린소프트는 친환경 소비 데이터를 분석해 리테일 기업에 인사이트를 제공합니다.",
      "mainTasks": "판매/재고 데이터 분석 및 리포팅 · 대시보드 지표 설계 · 데이터 파이프라인 협업",
      "requirements": "SQL 및 Python(pandas) 능숙자 · 데이터 분석 경력 2년 이상",
      "preferredPoints": "BI 툴 사용 경험 · 통계 분석 경험",
      "hireRounds": "서류전형 → 실무면접 → 최종면접",
      "benefits": "재택근무 주 2회 · 개인별 분석 서버 지급",
      "promoImages": [{ "label": "데이터팀", "bg": "#166534" }]
    },
    {
      "id": "j4",
      "companyId": "c4",
      "companyName": "파인애플커머스",
      "companyColor": "#f59e0b",
      "category": "기획/PM",
      "position": "서비스 기획자 (PM)",
      "location": "서울 마포구",
      "dueTime": null,
      "applyUrl": "https://example.com/careers/pineapple/pm",
      "skillTagIds": [6],
      "salary": { "newHire": 41000000, "average": 49000000 },
      "intro": "파인애플커머스는 도심형 새벽배송 인프라를 직접 구축/운영하는 커머스 기업입니다.",
      "mainTasks": "신규 기능 기획 및 요구사항 정의 · 유관부서 협업 및 일정 관리 · 서비스 지표 모니터링",
      "requirements": "서비스 기획 경력 2년 이상 · 데이터 기반 의사결정 경험",
      "preferredPoints": "커머스/물류 도메인 경험 · SQL 활용 가능자",
      "hireRounds": "서류전형 → 기획 과제 → 실무면접 → 최종면접",
      "benefits": "상시 채용, 즉시 입사 가능 · 전 직원 신선식품 정기구독 제공",
      "promoImages": [{ "label": "물류센터", "bg": "#b45309" }]
    },
    {
      "id": "j5",
      "companyId": "c5",
      "companyName": "오로라디자인",
      "companyColor": "#9333ea",
      "category": "디자인",
      "position": "UX/UI 디자이너",
      "location": "서울 용산구",
      "dueTime": "2026-08-20",
      "applyUrl": "https://example.com/careers/aurora/ux-designer",
      "skillTagIds": [11],
      "salary": { "newHire": 39000000, "average": 47000000 },
      "intro": "오로라디자인은 여러 핀테크 기업의 앱/웹 UX를 설계하는 전문 스튜디오입니다.",
      "mainTasks": "서비스 UX 리서치 및 와이어프레임 제작 · UI 디자인 및 프로토타이핑 · 개발팀과의 협업",
      "requirements": "UX/UI 디자인 경력 2년 이상 · Figma 능숙자",
      "preferredPoints": "금융/핀테크 서비스 디자인 경험 · 디자인 시스템 운영 경험",
      "hireRounds": "서류전형 → 포트폴리오 리뷰 → 실무면접 → 최종면접",
      "benefits": "최신 디자인 툴 라이선스 전 직원 지급 · 자유복장",
      "promoImages": [{ "label": "디자인 스튜디오", "bg": "#6b21a8" }]
    },
    {
      "id": "j6",
      "companyId": "c6",
      "companyName": "넥스트페이먼츠",
      "companyColor": "#1d4ed8",
      "category": "서버/백엔드",
      "position": "백엔드 개발자 (금융/결제)",
      "location": "서울 여의도",
      "dueTime": "2026-07-25",
      "applyUrl": "https://example.com/careers/nextpayments/backend",
      "skillTagIds": [14, 15, 10],
      "salary": { "newHire": 46000000, "average": 58000000 },
      "intro": "넥스트페이먼츠는 연 20조원 규모의 결제를 처리하는 결제 인프라 기업입니다.",
      "mainTasks": "결제 API 설계 및 개발 · 장애 대응 및 모니터링 체계 구축 · 정산 시스템 개발",
      "requirements": "금융/결제 도메인 백엔드 경력 3년 이상 · 대용량 트래픽 처리 경험",
      "preferredPoints": "PG/VAN 연동 경험 · MSA 설계 경험",
      "hireRounds": "서류전형 → 코딩테스트 → 실무면접 2회 → 임원면접",
      "benefits": "국내 최고 수준 연봉 · 스톡옵션 지급",
      "promoImages": [{ "label": "결제 인프라팀", "bg": "#1e40af" }]
    },
    {
      "id": "j7",
      "companyId": "c7",
      "companyName": "클라우드메이트",
      "companyColor": "#0f766e",
      "category": "인프라/DevOps",
      "position": "DevOps 엔지니어",
      "location": "경기 판교",
      "dueTime": "2026-08-10",
      "applyUrl": "https://example.com/careers/cloudmate/devops",
      "skillTagIds": [8, 9, 10, 13],
      "salary": { "newHire": 44000000, "average": 53000000 },
      "intro": "클라우드메이트는 여러 클라우드(AWS/GCP/Azure)를 통합 관리하는 SaaS를 제공합니다.",
      "mainTasks": "CI/CD 파이프라인 구축 및 운영 · 인프라 모니터링 체계 개선 · 비용 최적화",
      "requirements": "Kubernetes/Docker 운영 경험 · AWS 또는 GCP 실무 경험",
      "preferredPoints": "Terraform 등 IaC 경험 · 대규모 트래픽 서비스 운영 경험",
      "hireRounds": "서류전형 → 실무면접 → 최종면접",
      "benefits": "클라우드 자격증 취득 비용 전액 지원 · 유연근무제",
      "promoImages": [{ "label": "인프라팀", "bg": "#115e59" }]
    },
    {
      "id": "j8",
      "companyId": "c8",
      "companyName": "스퀘어푸드",
      "companyColor": "#db2777",
      "category": "마케팅",
      "position": "퍼포먼스 마케터",
      "location": "서울 송파구",
      "dueTime": "2026-07-28",
      "applyUrl": "https://example.com/careers/squarefood/marketer",
      "skillTagIds": [12],
      "salary": { "newHire": 38000000, "average": 45000000 },
      "intro": "스퀘어푸드는 1인가구를 위한 밀키트 정기구독 서비스를 운영하는 푸드테크 기업입니다.",
      "mainTasks": "퍼포먼스 광고 캠페인 기획/운영 · 데이터 기반 채널 최적화 · 콘텐츠 마케팅 협업",
      "requirements": "퍼포먼스 마케팅 경력 2년 이상 · GA 등 분석 툴 활용 가능자",
      "preferredPoints": "커머스/구독 서비스 마케팅 경험 · 데이터 분석 역량",
      "hireRounds": "서류전형 → 실무면접 → 최종면접",
      "benefits": "매달 자사 밀키트 무상 제공 · 우수사원 해외연수",
      "promoImages": [{ "label": "마케팅팀", "bg": "#be185d" }]
    }
  ],
  "candidates": [
    {
      "jobseekerId": "seed-1",
      "displayLabel": "지원자 A",
      "school": "한빛대학교",
      "major": "컴퓨터공학과",
      "gpa": 4.1,
      "gpaScale": 4.5,
      "skillTagIds": [1, 2, 3, 6],
      "careerHistory": [{ "company": "스타트업 인턴", "period": "2025.01-2025.06", "role": "백엔드", "isInternship": true }],
      "selfIntroId": "seed-si-1",
      "jobId": "j1",
      "content": "Django 기반 사이드 프로젝트를 운영하며 REST API 설계 경험을 쌓았습니다."
    },
    {
      "jobseekerId": "seed-2",
      "displayLabel": "지원자 B",
      "school": "강남대학교",
      "major": "소프트웨어학과",
      "gpa": 3.8,
      "gpaScale": 4.5,
      "skillTagIds": [4, 5],
      "careerHistory": [],
      "selfIntroId": "seed-si-2",
      "jobId": "j2",
      "content": "React와 TypeScript로 팀 프로젝트 대시보드를 구현한 경험이 있습니다."
    },
    {
      "jobseekerId": "seed-3",
      "displayLabel": "지원자 C",
      "school": "서한대학교",
      "major": "산업공학과",
      "gpa": 4.3,
      "gpaScale": 4.3,
      "skillTagIds": [6, 7],
      "careerHistory": [{ "company": "데이터랩", "period": "2024.07-2024.12", "role": "데이터 분석 인턴", "isInternship": true }],
      "selfIntroId": "seed-si-3",
      "jobId": "j3",
      "content": "pandas로 판매 데이터를 분석해 재고 최적화 리포트를 작성한 경험이 있습니다."
    },
    {
      "jobseekerId": "seed-4",
      "displayLabel": "지원자 D",
      "school": "한빛대학교",
      "major": "컴퓨터공학과",
      "gpa": 3.6,
      "gpaScale": 4.5,
      "skillTagIds": [8, 9, 10],
      "careerHistory": [{ "company": "클라우드 스타트업", "period": "2024.01-2024.12", "role": "인프라", "isInternship": false }],
      "selfIntroId": "seed-si-4",
      "jobId": "j7",
      "content": "Kubernetes 클러스터 운영 및 CI/CD 파이프라인 구축 경험이 있습니다."
    },
    {
      "jobseekerId": "seed-5",
      "displayLabel": "지원자 E",
      "school": "동서대학교",
      "major": "디자인학과",
      "gpa": 4.0,
      "gpaScale": 4.5,
      "skillTagIds": [11],
      "careerHistory": [],
      "selfIntroId": "seed-si-5",
      "jobId": "j5",
      "content": "핀테크 서비스 UX 리서치 프로젝트에 참여해 와이어프레임을 제작했습니다."
    },
    {
      "jobseekerId": "seed-6",
      "displayLabel": "지원자 F",
      "school": "강남대학교",
      "major": "경영학과",
      "gpa": 3.9,
      "gpaScale": 4.5,
      "skillTagIds": [12],
      "careerHistory": [{ "company": "이커머스 스타트업", "period": "2025.03-2025.08", "role": "마케팅 인턴", "isInternship": true }],
      "selfIntroId": "seed-si-6",
      "jobId": "j8",
      "content": "퍼포먼스 마케팅 캠페인을 직접 운영하며 GA로 채널별 성과를 분석했습니다."
    }
  ],
  "seedScoutTemplates": [
    {
      "companyId": "c1",
      "companyName": "테크노바",
      "message": "프로필을 보고 백엔드 포지션에 관심이 있으실 것 같아 제안드립니다. 편하실 때 확인 부탁드려요."
    },
    {
      "companyId": "c7",
      "companyName": "클라우드메이트",
      "message": "인프라/DevOps 직군에서 좋은 시너지를 낼 수 있을 것 같아 스카웃 제안을 드립니다."
    }
  ]
}
